{
    "description": "",
    "tags": [
        {
            "id": 90625232,
            "tagId": 28654265,
            "name": "train",
            "value": null,
            "labelerLogin": "tyra1014",
            "createdAt": "2020-10-17T23:35:32.080Z",
            "updatedAt": "2020-10-17T23:35:32.080Z"
        }
    ],
    "size": {
        "height": 224,
        "width": 224
    },
    "objects": [
        {
            "id": 544218188,
            "classId": 2537979,
            "description": "",
            "geometryType": "rectangle",
            "labelerLogin": "tyra1014",
            "createdAt": "2020-10-18T23:24:44.712Z",
            "updatedAt": "2020-10-18T23:24:44.712Z",
            "tags": [],
            "classTitle": "road",
            "points": {
                "exterior": [
                    [
                        0,
                        90.78125
                    ],
                    [
                        223.890625,
                        223.78125
                    ]
                ],
                "interior": []
            }
        },
        {
            "id": 544218182,
            "classId": 2537982,
            "description": "",
            "geometryType": "rectangle",
            "labelerLogin": "tyra1014",
            "createdAt": "2020-10-18T23:24:44.712Z",
            "updatedAt": "2020-10-18T23:24:44.712Z",
            "tags": [],
            "classTitle": "building",
            "points": {
                "exterior": [
                    [
                        0,
                        0
                    ],
                    [
                        100.84375,
                        113.53125
                    ]
                ],
                "interior": []
            }
        },
        {
            "id": 544218178,
            "classId": 2537982,
            "description": "",
            "geometryType": "rectangle",
            "labelerLogin": "tyra1014",
            "createdAt": "2020-10-18T23:24:44.711Z",
            "updatedAt": "2020-10-18T23:24:44.711Z",
            "tags": [],
            "classTitle": "building",
            "points": {
                "exterior": [
                    [
                        118.34375,
                        0
                    ],
                    [
                        223.890625,
                        126.65625
                    ]
                ],
                "interior": []
            }
        },
        {
            "id": 544218168,
            "classId": 2537979,
            "description": "",
            "geometryType": "rectangle",
            "labelerLogin": "tyra1014",
            "createdAt": "2020-10-18T23:24:44.711Z",
            "updatedAt": "2020-10-18T23:24:44.711Z",
            "tags": [],
            "classTitle": "road",
            "points": {
                "exterior": [
                    [
                        69.453125,
                        101.28125
                    ],
                    [
                        98.4375,
                        117.90625
                    ]
                ],
                "interior": []
            }
        },
        {
            "id": 544218164,
            "classId": 2537981,
            "description": "",
            "geometryType": "rectangle",
            "labelerLogin": "tyra1014",
            "createdAt": "2020-10-18T23:24:44.710Z",
            "updatedAt": "2020-10-18T23:24:44.710Z",
            "tags": [],
            "classTitle": "vehicle",
            "points": {
                "exterior": [
                    [
                        68.6875,
                        94.5
                    ],
                    [
                        82.46875,
                        113.96875
                    ]
                ],
                "interior": []
            }
        },
        {
            "id": 544218163,
            "classId": 2537981,
            "description": "",
            "geometryType": "rectangle",
            "labelerLogin": "tyra1014",
            "createdAt": "2020-10-18T23:24:44.710Z",
            "updatedAt": "2020-10-18T23:24:44.710Z",
            "tags": [],
            "classTitle": "vehicle",
            "points": {
                "exterior": [
                    [
                        95.046875,
                        93.625
                    ],
                    [
                        103.90625,
                        108.5
                    ]
                ],
                "interior": []
            }
        },
        {
            "id": 544218154,
            "classId": 2537981,
            "description": "",
            "geometryType": "rectangle",
            "labelerLogin": "tyra1014",
            "createdAt": "2020-10-18T23:24:44.710Z",
            "updatedAt": "2020-10-18T23:24:44.710Z",
            "tags": [],
            "classTitle": "vehicle",
            "points": {
                "exterior": [
                    [
                        41.671875,
                        96.46875
                    ],
                    [
                        54.90625,
                        121.625
                    ]
                ],
                "interior": []
            }
        },
        {
            "id": 544218153,
            "classId": 2537981,
            "description": "",
            "geometryType": "rectangle",
            "labelerLogin": "tyra1014",
            "createdAt": "2020-10-18T23:24:44.710Z",
            "updatedAt": "2020-10-18T23:24:44.710Z",
            "tags": [],
            "classTitle": "vehicle",
            "points": {
                "exterior": [
                    [
                        3.71875,
                        89.03125
                    ],
                    [
                        42.328125,
                        120.53125
                    ]
                ],
                "interior": []
            }
        },
        {
            "id": 544218152,
            "classId": 2537981,
            "description": "",
            "geometryType": "rectangle",
            "labelerLogin": "tyra1014",
            "createdAt": "2020-10-18T23:24:44.710Z",
            "updatedAt": "2020-10-18T23:24:44.710Z",
            "tags": [],
            "classTitle": "vehicle",
            "points": {
                "exterior": [
                    [
                        0,
                        89.6875
                    ],
                    [
                        8.859375,
                        125.34375
                    ]
                ],
                "interior": []
            }
        },
        {
            "id": 544218147,
            "classId": 2537981,
            "description": "",
            "geometryType": "rectangle",
            "labelerLogin": "tyra1014",
            "createdAt": "2020-10-18T23:24:44.709Z",
            "updatedAt": "2020-10-18T23:24:44.709Z",
            "tags": [],
            "classTitle": "vehicle",
            "points": {
                "exterior": [
                    [
                        9.734375,
                        103.6875
                    ],
                    [
                        47.03125,
                        140
                    ]
                ],
                "interior": []
            }
        },
        {
            "id": 544218136,
            "classId": 2537981,
            "description": "",
            "geometryType": "rectangle",
            "labelerLogin": "tyra1014",
            "createdAt": "2020-10-18T23:24:44.708Z",
            "updatedAt": "2020-10-18T23:24:44.708Z",
            "tags": [],
            "classTitle": "vehicle",
            "points": {
                "exterior": [
                    [
                        0,
                        94.71875
                    ],
                    [
                        9.296875,
                        161.875
                    ]
                ],
                "interior": []
            }
        },
        {
            "id": 544218134,
            "classId": 2537981,
            "description": "",
            "geometryType": "rectangle",
            "labelerLogin": "tyra1014",
            "createdAt": "2020-10-18T23:24:44.707Z",
            "updatedAt": "2020-10-18T23:24:44.707Z",
            "tags": [],
            "classTitle": "vehicle",
            "points": {
                "exterior": [
                    [
                        127.53125,
                        78.53125
                    ],
                    [
                        137.921875,
                        108.71875
                    ]
                ],
                "interior": []
            }
        },
        {
            "id": 544218133,
            "classId": 2537981,
            "description": "",
            "geometryType": "rectangle",
            "labelerLogin": "tyra1014",
            "createdAt": "2020-10-18T23:24:44.707Z",
            "updatedAt": "2020-10-18T23:24:44.707Z",
            "tags": [],
            "classTitle": "vehicle",
            "points": {
                "exterior": [
                    [
                        134.859375,
                        90.34375
                    ],
                    [
                        141.421875,
                        119
                    ]
                ],
                "interior": []
            }
        },
        {
            "id": 544218131,
            "classId": 2537982,
            "description": "",
            "geometryType": "rectangle",
            "labelerLogin": "tyra1014",
            "createdAt": "2020-10-18T23:24:44.707Z",
            "updatedAt": "2020-10-18T23:24:44.707Z",
            "tags": [],
            "classTitle": "building",
            "points": {
                "exterior": [
                    [
                        140,
                        40.90625
                    ],
                    [
                        188.125,
                        131.03125
                    ]
                ],
                "interior": []
            }
        },
        {
            "id": 544218113,
            "classId": 2537981,
            "description": "",
            "geometryType": "rectangle",
            "labelerLogin": "tyra1014",
            "createdAt": "2020-10-18T23:24:44.704Z",
            "updatedAt": "2020-10-18T23:24:44.704Z",
            "tags": [],
            "classTitle": "vehicle",
            "points": {
                "exterior": [
                    [
                        182.765625,
                        100.625
                    ],
                    [
                        211.75,
                        142.84375
                    ]
                ],
                "interior": []
            }
        }
    ]
}