{
    "description": "",
    "tags": [
        {
            "id": 90624913,
            "tagId": 28654265,
            "name": "train",
            "value": null,
            "labelerLogin": "tyra1014",
            "createdAt": "2020-10-17T23:35:09.857Z",
            "updatedAt": "2020-10-17T23:35:09.857Z"
        }
    ],
    "size": {
        "height": 224,
        "width": 224
    },
    "objects": [
        {
            "id": 544197355,
            "classId": 2537979,
            "description": "",
            "geometryType": "rectangle",
            "labelerLogin": "tyra1014",
            "createdAt": "2020-10-18T23:24:35.776Z",
            "updatedAt": "2020-10-18T23:24:35.776Z",
            "tags": [],
            "classTitle": "road",
            "points": {
                "exterior": [
                    [
                        0,
                        44.84375
                    ],
                    [
                        223.890625,
                        223.78125
                    ]
                ],
                "interior": []
            }
        },
        {
            "id": 544197352,
            "classId": 2537982,
            "description": "",
            "geometryType": "rectangle",
            "labelerLogin": "tyra1014",
            "createdAt": "2020-10-18T23:24:35.775Z",
            "updatedAt": "2020-10-18T23:24:35.775Z",
            "tags": [],
            "classTitle": "building",
            "points": {
                "exterior": [
                    [
                        0,
                        0
                    ],
                    [
                        217.4375,
                        96.25
                    ]
                ],
                "interior": []
            }
        },
        {
            "id": 544197351,
            "classId": 2537982,
            "description": "",
            "geometryType": "rectangle",
            "labelerLogin": "tyra1014",
            "createdAt": "2020-10-18T23:24:35.775Z",
            "updatedAt": "2020-10-18T23:24:35.775Z",
            "tags": [],
            "classTitle": "building",
            "points": {
                "exterior": [
                    [
                        181.5625,
                        0
                    ],
                    [
                        223.890625,
                        92.96875
                    ]
                ],
                "interior": []
            }
        },
        {
            "id": 544197323,
            "classId": 2537981,
            "description": "",
            "geometryType": "rectangle",
            "labelerLogin": "tyra1014",
            "createdAt": "2020-10-18T23:24:35.769Z",
            "updatedAt": "2020-10-18T23:24:35.769Z",
            "tags": [],
            "classTitle": "vehicle",
            "points": {
                "exterior": [
                    [
                        142.1875,
                        77.4375
                    ],
                    [
                        154.21875,
                        92.3125
                    ]
                ],
                "interior": []
            }
        },
        {
            "id": 544197322,
            "classId": 2537981,
            "description": "",
            "geometryType": "rectangle",
            "labelerLogin": "tyra1014",
            "createdAt": "2020-10-18T23:24:35.769Z",
            "updatedAt": "2020-10-18T23:24:35.769Z",
            "tags": [],
            "classTitle": "vehicle",
            "points": {
                "exterior": [
                    [
                        161.875,
                        74.8125
                    ],
                    [
                        172.921875,
                        93.84375
                    ]
                ],
                "interior": []
            }
        },
        {
            "id": 544197321,
            "classId": 2537981,
            "description": "",
            "geometryType": "rectangle",
            "labelerLogin": "tyra1014",
            "createdAt": "2020-10-18T23:24:35.768Z",
            "updatedAt": "2020-10-18T23:24:35.768Z",
            "tags": [],
            "classTitle": "vehicle",
            "points": {
                "exterior": [
                    [
                        148.203125,
                        74.15625
                    ],
                    [
                        168.4375,
                        103.46875
                    ]
                ],
                "interior": []
            }
        },
        {
            "id": 544197319,
            "classId": 2537981,
            "description": "",
            "geometryType": "rectangle",
            "labelerLogin": "tyra1014",
            "createdAt": "2020-10-18T23:24:35.768Z",
            "updatedAt": "2020-10-18T23:24:35.768Z",
            "tags": [],
            "classTitle": "vehicle",
            "points": {
                "exterior": [
                    [
                        177.296875,
                        71.3125
                    ],
                    [
                        187.46875,
                        83.78125
                    ]
                ],
                "interior": []
            }
        },
        {
            "id": 544197312,
            "classId": 2537979,
            "description": "",
            "geometryType": "rectangle",
            "labelerLogin": "tyra1014",
            "createdAt": "2020-10-18T23:24:35.768Z",
            "updatedAt": "2020-10-18T23:24:35.768Z",
            "tags": [],
            "classTitle": "road",
            "points": {
                "exterior": [
                    [
                        187.578125,
                        92.53125
                    ],
                    [
                        223.890625,
                        114.625
                    ]
                ],
                "interior": []
            }
        },
        {
            "id": 544197307,
            "classId": 2537981,
            "description": "",
            "geometryType": "rectangle",
            "labelerLogin": "tyra1014",
            "createdAt": "2020-10-18T23:24:35.767Z",
            "updatedAt": "2020-10-18T23:24:35.767Z",
            "tags": [],
            "classTitle": "vehicle",
            "points": {
                "exterior": [
                    [
                        203.4375,
                        71.96875
                    ],
                    [
                        223.890625,
                        107.84375
                    ]
                ],
                "interior": []
            }
        }
    ]
}